{
  "zip": "V6E 0C3",
  "sector": "Basic Materials",
  "longBusinessSummary": "Baru Gold Corp. operates as a mineral exploration company in Indonesia. The company holds a 70% interest in Sangihe gold-silver project, which is located on the island of Sangihe covering an area of 42,000 hectares. It also holds interest in the Miwah gold project that consists of three contiguous mining business permits covering 30,000 hectares located southeast of Banda Aceh in Aceh Province. The company was formerly known as East Asia Minerals Corporation and changed its name to Baru Gold Corp. in October 2020. Baru Gold Corp. is headquartered in Vancouver, Canada.",
  "city": "Vancouver",
  "phone": "604-684-2183",
  "state": "BC",
  "country": "Canada",
  "companyOfficers": [],
  "website": "http://www.barugoldcorp.com",
  "maxAge": 1,
  "address1": "1021 West Hastings Street",
  "fax": "888-371-5832",
  "industry": "Gold",
  "address2": "9th Floor",
  "previousClose": 0.12,
  "regularMarketOpen": 0.12,
  "twoHundredDayAverage": null,
  "trailingAnnualDividendYield": null,
  "payoutRatio": 0,
  "volume24Hr": null,
  "regularMarketDayHigh": 0.1244,
  "navPrice": null,
  "averageDailyVolume10Day": null,
  "totalAssets": null,
  "regularMarketPreviousClose": 0.12,
  "fiftyDayAverage": null,
  "trailingAnnualDividendRate": null,
  "open": 0.12,
  "averageVolume10days": null,
  "expireDate": null,
  "yield": null,
  "algorithm": null,
  "dividendRate": null,
  "exDividendDate": 1192579200,
  "beta": 0.6066,
  "circulatingSupply": null,
  "startDate": null,
  "regularMarketDayLow": 0.12,
  "priceHint": 4,
  "currency": "USD",
  "regularMarketVolume": 160910,
  "lastMarket": null,
  "maxSupply": null,
  "openInterest": null,
  "marketCap": 18165134,
  "volumeAllCurrencies": null,
  "strikePrice": null,
  "averageVolume": null,
  "priceToSalesTrailing12Months": null,
  "dayLow": 0.12,
  "ask": null,
  "ytdReturn": null,
  "askSize": null,
  "volume": 160910,
  "fiftyTwoWeekHigh": 0.1244,
  "forwardPE": null,
  "fromCurrency": null,
  "fiveYearAvgDividendYield": null,
  "fiftyTwoWeekLow": 0.12,
  "bid": null,
  "tradeable": false,
  "dividendYield": null,
  "bidSize": null,
  "dayHigh": 0.1244,
  "exchange": "PNK",
  "shortName": "BARU GOLD CORP",
  "longName": "Baru Gold Corp.",
  "exchangeTimezoneName": "America/New_York",
  "exchangeTimezoneShortName": "EST",
  "isEsgPopulated": false,
  "gmtOffSetMilliseconds": "-18000000",
  "underlyingSymbol": null,
  "quoteType": "EQUITY",
  "symbol": "BARUF",
  "underlyingExchangeSymbol": null,
  "headSymbol": null,
  "messageBoardId": "finmb_22143504",
  "uuid": "6e2adfd6-d0f6-3921-9259-278e9f7e12db",
  "market": "us_market",
  "annualHoldingsTurnover": null,
  "enterpriseToRevenue": null,
  "beta3Year": null,
  "profitMargins": 0,
  "enterpriseToEbitda": null,
  "52WeekChange": null,
  "morningStarRiskRating": null,
  "forwardEps": null,
  "revenueQuarterlyGrowth": null,
  "sharesOutstanding": 148208992,
  "fundInceptionDate": null,
  "annualReportExpenseRatio": null,
  "bookValue": null,
  "sharesShort": null,
  "sharesPercentSharesOut": null,
  "fundFamily": null,
  "lastFiscalYearEnd": 1598832000,
  "heldPercentInstitutions": 0.075100005,
  "netIncomeToCommon": null,
  "trailingEps": null,
  "lastDividendValue": null,
  "SandP52WeekChange": null,
  "priceToBook": null,
  "heldPercentInsiders": 0.039890002,
  "nextFiscalYearEnd": 1661904000,
  "mostRecentQuarter": 1598832000,
  "shortRatio": null,
  "sharesShortPreviousMonthDate": null,
  "floatShares": 168446411,
  "enterpriseValue": 21304128,
  "threeYearAverageReturn": null,
  "lastSplitDate": null,
  "lastSplitFactor": null,
  "legalType": null,
  "morningStarOverallRating": null,
  "earningsQuarterlyGrowth": null,
  "dateShortInterest": null,
  "pegRatio": null,
  "lastCapGain": null,
  "shortPercentOfFloat": null,
  "sharesShortPriorMonth": null,
  "category": null,
  "fiveYearAverageReturn": null,
  "regularMarketPrice": 0.12,
  "logo_url": "https://logo.clearbit.com/barugoldcorp.com"
}