{
  "zip": "M5C 1P1",
  "sector": "",
  "fullTimeEmployees": 2,
  "longBusinessSummary": "Bunker Hill Mining Corp., an exploration stage company, engages in the acquisition and exploration of mining properties. The company focuses on exploring for zinc, lead, and silver ores. It holds an option agreement to acquire a 100% interest in the Bunker Hill mine, which includes 440 patented mining claims covering an area of approximately 5700 acres located in Idaho. The company was formerly known as Liberty Silver Corp. and changed its name to Bunker Hill Mining Corp. in September 2017. Bunker Hill Mining Corp. was founded in 2007 and is headquartered in Toronto, Canada.",
  "city": "Toronto",
  "phone": "416-477-7771",
  "state": "ON",
  "country": "Canada",
  "companyOfficers": [],
  "website": "http://www.bunkerhillmining.com",
  "maxAge": 1,
  "address1": "82 Richmond Street East",
  "industry": "",
  "previousClose": 0.4789,
  "regularMarketOpen": 0.47716,
  "twoHundredDayAverage": 0.4372,
  "trailingAnnualDividendYield": null,
  "payoutRatio": null,
  "volume24Hr": null,
  "regularMarketDayHigh": 0.47716,
  "navPrice": null,
  "averageDailyVolume10Day": 16780,
  "totalAssets": null,
  "regularMarketPreviousClose": 0.4789,
  "fiftyDayAverage": 0.4372,
  "trailingAnnualDividendRate": null,
  "open": 0.47716,
  "averageVolume10days": 16780,
  "expireDate": null,
  "yield": null,
  "algorithm": null,
  "dividendRate": null,
  "exDividendDate": null,
  "beta": 9.91334,
  "circulatingSupply": null,
  "startDate": null,
  "regularMarketDayLow": 0.41543,
  "priceHint": 4,
  "currency": "USD",
  "regularMarketVolume": 22544,
  "lastMarket": null,
  "maxSupply": null,
  "openInterest": null,
  "marketCap": 1759267,
  "volumeAllCurrencies": null,
  "strikePrice": null,
  "averageVolume": 16780,
  "priceToSalesTrailing12Months": null,
  "dayLow": 0.41543,
  "ask": 0,
  "ytdReturn": null,
  "askSize": 0,
  "volume": 22544,
  "fiftyTwoWeekHigh": 0.479,
  "forwardPE": null,
  "fromCurrency": null,
  "fiveYearAvgDividendYield": null,
  "fiftyTwoWeekLow": 0.39,
  "bid": 0,
  "tradeable": false,
  "dividendYield": null,
  "bidSize": 0,
  "dayHigh": 0.47716,
  "exchange": "PNK",
  "shortName": "BUNKER HILL MINING CORP",
  "longName": "Bunker Hill Mining Corp.",
  "exchangeTimezoneName": "America/New_York",
  "exchangeTimezoneShortName": "EST",
  "isEsgPopulated": false,
  "gmtOffSetMilliseconds": "-18000000",
  "underlyingSymbol": null,
  "quoteType": "EQUITY",
  "symbol": "BHLL",
  "underlyingExchangeSymbol": null,
  "headSymbol": null,
  "messageBoardId": "finmb_40114098",
  "uuid": "cead5c2c-9208-38d3-a1ae-14cb2887f760",
  "market": "us_market",
  "annualHoldingsTurnover": null,
  "enterpriseToRevenue": null,
  "beta3Year": null,
  "profitMargins": 0,
  "enterpriseToEbitda": -4.145,
  "52WeekChange": null,
  "morningStarRiskRating": null,
  "forwardEps": null,
  "revenueQuarterlyGrowth": null,
  "sharesOutstanding": 4151400,
  "fundInceptionDate": null,
  "annualReportExpenseRatio": null,
  "bookValue": -0.235,
  "sharesShort": null,
  "sharesPercentSharesOut": null,
  "fundFamily": null,
  "lastFiscalYearEnd": 1593475200,
  "heldPercentInstitutions": 0.33168998,
  "netIncomeToCommon": -26658942,
  "trailingEps": -0.322,
  "lastDividendValue": null,
  "SandP52WeekChange": null,
  "priceToBook": null,
  "heldPercentInsiders": 0.23926,
  "nextFiscalYearEnd": 1656547200,
  "mostRecentQuarter": 1601424000,
  "shortRatio": null,
  "sharesShortPreviousMonthDate": null,
  "floatShares": 121764001,
  "enterpriseValue": 61694592,
  "threeYearAverageReturn": null,
  "lastSplitDate": null,
  "lastSplitFactor": null,
  "legalType": null,
  "morningStarOverallRating": null,
  "earningsQuarterlyGrowth": null,
  "dateShortInterest": null,
  "pegRatio": null,
  "lastCapGain": null,
  "shortPercentOfFloat": null,
  "sharesShortPriorMonth": null,
  "category": null,
  "fiveYearAverageReturn": null,
  "regularMarketPrice": 0.47716,
  "logo_url": "https://logo.clearbit.com/bunkerhillmining.com"
}