{
  "zip": "58492",
  "sector": "Financial Services",
  "fullTimeEmployees": 1,
  "longBusinessSummary": "First Bitcoin Capital Corp. engages in the business of digital cryptocurrency and blockchain development. The company owns and operates various digital assets, including First Bitcoin Incubator, which helps entrepreneurs with the fundraising, partnerships, networking, advice, and vetting needs to expand their businesses; 420WiFi that connects dispensaries to their clients in real time; CoinQX, a cryptocurrency exchange that offers traders the option of creating a digital wallet to begin trading; BitMiner, which manages bitcoin and other crypto-currency mining operations; ALT Coin Market Cap, an currency exchange; Bit Cann Pay that provides check cashing ATM's services to cannabis dispensaries; iCoinNews, an online news platform that gathers real time news about bitcoin and blockchain technology; and Kiosks, an automated check-cashing kiosks through BITCF locations in Northern California. It has agreements with third parties to develop blockchains to track petroleum and agricultural supply chain management. The company was formerly known as Grand Pacaraima Gold Corp. and changed its name to First Bitcoin Capital Corp. in February 2014. First Bitcoin Capital Corp. was founded in 1989 and is based in Holon, Israel.",
  "city": "Holon",
  "phone": "972 55 9661110",
  "country": "Israel",
  "companyOfficers": [],
  "website": "http://firstbitcoin.io",
  "maxAge": 1,
  "address1": "Har Hatzofim 24/4",
  "industry": "Capital Markets",
  "previousClose": 0.115,
  "regularMarketOpen": 0.13,
  "twoHundredDayAverage": 0.12595643,
  "trailingAnnualDividendYield": null,
  "payoutRatio": null,
  "volume24Hr": null,
  "regularMarketDayHigh": 0.13,
  "navPrice": null,
  "averageDailyVolume10Day": 616136,
  "totalAssets": null,
  "regularMarketPreviousClose": 0.115,
  "fiftyDayAverage": 0.083851516,
  "trailingAnnualDividendRate": null,
  "open": 0.13,
  "averageVolume10days": 616136,
  "expireDate": null,
  "yield": null,
  "algorithm": null,
  "dividendRate": null,
  "exDividendDate": null,
  "beta": 1.547268,
  "circulatingSupply": null,
  "startDate": null,
  "regularMarketDayLow": 0.1,
  "priceHint": 4,
  "currency": "USD",
  "regularMarketVolume": 622275,
  "lastMarket": null,
  "maxSupply": null,
  "openInterest": null,
  "marketCap": 30208000,
  "volumeAllCurrencies": null,
  "strikePrice": null,
  "averageVolume": 177334,
  "priceToSalesTrailing12Months": "Infinity",
  "dayLow": 0.1,
  "ask": 0,
  "ytdReturn": null,
  "askSize": 0,
  "volume": 622275,
  "fiftyTwoWeekHigh": 1.39,
  "forwardPE": null,
  "fromCurrency": null,
  "fiveYearAvgDividendYield": null,
  "fiftyTwoWeekLow": 0.014,
  "bid": 0,
  "tradeable": false,
  "dividendYield": null,
  "bidSize": 0,
  "dayHigh": 0.13,
  "exchange": "PNK",
  "shortName": "FIRST BITCOIN CAP CORP",
  "longName": "First Bitcoin Capital Corp.",
  "exchangeTimezoneName": "America/New_York",
  "exchangeTimezoneShortName": "EST",
  "isEsgPopulated": false,
  "gmtOffSetMilliseconds": "-18000000",
  "underlyingSymbol": null,
  "quoteType": "EQUITY",
  "symbol": "BITCF",
  "underlyingExchangeSymbol": null,
  "headSymbol": null,
  "messageBoardId": "finmb_22930587",
  "uuid": "dc431934-bbd4-3fb5-86ba-c9f8879fe7db",
  "market": "us_market",
  "annualHoldingsTurnover": null,
  "enterpriseToRevenue": null,
  "beta3Year": null,
  "profitMargins": 0,
  "enterpriseToEbitda": -196.282,
  "52WeekChange": null,
  "morningStarRiskRating": null,
  "forwardEps": null,
  "revenueQuarterlyGrowth": null,
  "sharesOutstanding": 302080000,
  "fundInceptionDate": null,
  "annualReportExpenseRatio": null,
  "bookValue": 0.002,
  "sharesShort": null,
  "sharesPercentSharesOut": null,
  "fundFamily": null,
  "lastFiscalYearEnd": 1546214400,
  "heldPercentInstitutions": 0,
  "netIncomeToCommon": -473327,
  "trailingEps": -0.002,
  "lastDividendValue": null,
  "SandP52WeekChange": null,
  "priceToBook": 50,
  "heldPercentInsiders": 0,
  "nextFiscalYearEnd": 1609372800,
  "mostRecentQuarter": 1569801600,
  "shortRatio": null,
  "sharesShortPreviousMonthDate": null,
  "floatShares": 103397801,
  "enterpriseValue": 34902628,
  "threeYearAverageReturn": null,
  "lastSplitDate": null,
  "lastSplitFactor": null,
  "legalType": null,
  "morningStarOverallRating": null,
  "earningsQuarterlyGrowth": 0.048,
  "dateShortInterest": null,
  "pegRatio": null,
  "lastCapGain": null,
  "shortPercentOfFloat": null,
  "sharesShortPriorMonth": null,
  "category": null,
  "fiveYearAverageReturn": null,
  "regularMarketPrice": 0.13,
  "logo_url": "https://logo.clearbit.com/firstbitcoin.io"
}