{
  "zip": "92691",
  "sector": "Healthcare",
  "longBusinessSummary": "The CannaBusiness Group, Inc. operates as a real estate acquisition, leasing, and management company focusing on zoning issues in the United States. The company acquires commercial property or land, and leases out the facilities for customers in the agricultural, industrial, commercial, and retail sectors. It also acquires, leases, and manages a portfolio of properties. The company was formerly known as Muscle Warfare International, Inc. and changed its name to The CannaBusiness Group, Inc. in February 2014. The CannaBusiness Group, Inc. was founded in 1985 and is based in Mission Viejo, California.",
  "city": "Mission Viejo",
  "phone": "888-932-2444",
  "state": "CA",
  "country": "United States",
  "companyOfficers": [],
  "maxAge": 1,
  "address1": "27758 Santa Margarita Parkway",
  "industry": "Drug Manufacturers—Specialty & Generic",
  "address2": "Suite 141",
  "previousClose": 0.0007,
  "regularMarketOpen": 0.0007,
  "twoHundredDayAverage": 0.0007832143,
  "trailingAnnualDividendYield": null,
  "payoutRatio": null,
  "volume24Hr": null,
  "regularMarketDayHigh": 0.0007,
  "navPrice": null,
  "averageDailyVolume10Day": 231293,
  "totalAssets": null,
  "regularMarketPreviousClose": 0.0007,
  "fiftyDayAverage": 0.00072727277,
  "trailingAnnualDividendRate": null,
  "open": 0.0007,
  "averageVolume10days": 231293,
  "expireDate": null,
  "yield": null,
  "algorithm": null,
  "dividendRate": null,
  "exDividendDate": null,
  "beta": -4.843487,
  "circulatingSupply": null,
  "startDate": null,
  "regularMarketDayLow": 0.0007,
  "priceHint": 4,
  "currency": "USD",
  "regularMarketVolume": 6166,
  "lastMarket": null,
  "maxSupply": null,
  "openInterest": null,
  "marketCap": 124959,
  "volumeAllCurrencies": null,
  "strikePrice": null,
  "averageVolume": 92657,
  "priceToSalesTrailing12Months": 0.07745879,
  "dayLow": 0.0007,
  "ask": 0,
  "ytdReturn": null,
  "askSize": 0,
  "volume": 6166,
  "fiftyTwoWeekHigh": 0.009,
  "forwardPE": null,
  "fromCurrency": null,
  "fiveYearAvgDividendYield": null,
  "fiftyTwoWeekLow": 2e-05,
  "bid": 0,
  "tradeable": false,
  "dividendYield": 0.0311,
  "bidSize": 0,
  "dayHigh": 0.0007,
  "exchange": "PNK",
  "shortName": "CANNABUSINESS GROUP INC",
  "longName": "The CannaBusiness Group, Inc.",
  "exchangeTimezoneName": "America/New_York",
  "exchangeTimezoneShortName": "EST",
  "isEsgPopulated": false,
  "gmtOffSetMilliseconds": "-18000000",
  "underlyingSymbol": null,
  "quoteType": "EQUITY",
  "symbol": "CBGI",
  "underlyingExchangeSymbol": null,
  "headSymbol": null,
  "messageBoardId": "finmb_29397101",
  "uuid": "e8b53c60-b034-3d3b-8eb1-66947307763b",
  "market": "us_market",
  "annualHoldingsTurnover": null,
  "enterpriseToRevenue": null,
  "beta3Year": null,
  "profitMargins": -0.32498002,
  "enterpriseToEbitda": null,
  "52WeekChange": null,
  "morningStarRiskRating": null,
  "forwardEps": null,
  "revenueQuarterlyGrowth": null,
  "sharesOutstanding": 0,
  "fundInceptionDate": null,
  "annualReportExpenseRatio": null,
  "bookValue": null,
  "sharesShort": null,
  "sharesPercentSharesOut": null,
  "fundFamily": null,
  "lastFiscalYearEnd": 1356912000,
  "heldPercentInstitutions": null,
  "netIncomeToCommon": -524264,
  "trailingEps": null,
  "lastDividendValue": null,
  "SandP52WeekChange": null,
  "priceToBook": null,
  "heldPercentInsiders": null,
  "nextFiscalYearEnd": 1419984000,
  "mostRecentQuarter": 1364688000,
  "shortRatio": null,
  "sharesShortPreviousMonthDate": null,
  "floatShares": null,
  "enterpriseValue": null,
  "threeYearAverageReturn": null,
  "lastSplitDate": 1390348800,
  "lastSplitFactor": "3:1",
  "legalType": null,
  "morningStarOverallRating": null,
  "earningsQuarterlyGrowth": null,
  "dateShortInterest": null,
  "pegRatio": null,
  "lastCapGain": null,
  "shortPercentOfFloat": null,
  "sharesShortPriorMonth": null,
  "category": null,
  "fiveYearAverageReturn": null,
  "regularMarketPrice": 0.0007,
  "logo_url": ""
}