{
  "zip": "35124",
  "sector": "",
  "longBusinessSummary": "Cyber Operations, Inc., a technology company, develops integrated security technology tools for government, commercial enterprises, and financial institutions in the United States. The company's products include Cyber ACL, an enterprise level solution, which allows organizations to store, control, and implement access lists for various brands and types of networking devices from one centrally managed database with revision history and access control, as well as provides tools for creating, analyzing, and deploying access control policies, including comparison, searching, conflict detection, hierarchal lists, and simultaneous synchronization of devices with the database. It also offers Cyber DAN, a digital signage system, which delivers digital media, such as video ads, stills, RSS feeds, educational programming, and product demonstrations directly to digital display locations at stores, restaurants, branch offices, company desktops, and other locations. Cyber Operations, Inc. was founded in 1999 and is headquartered in Pelham, Alabama.",
  "city": "Pelham",
  "phone": "205-733-0902",
  "state": "AL",
  "country": "United States",
  "companyOfficers": [],
  "website": "http://www.cyberoperations.com",
  "maxAge": 1,
  "address1": "153 Cahaba Valley Parkway",
  "fax": "205-733-8445",
  "industry": "",
  "previousClose": 0.0025,
  "regularMarketOpen": 0.0025,
  "twoHundredDayAverage": 0.0026326086,
  "trailingAnnualDividendYield": null,
  "payoutRatio": null,
  "volume24Hr": null,
  "regularMarketDayHigh": 0.0025,
  "navPrice": null,
  "averageDailyVolume10Day": 0,
  "totalAssets": null,
  "regularMarketPreviousClose": 0.0025,
  "fiftyDayAverage": 0.0017272728,
  "trailingAnnualDividendRate": null,
  "open": 0.0025,
  "averageVolume10days": 0,
  "expireDate": null,
  "yield": null,
  "algorithm": null,
  "dividendRate": null,
  "exDividendDate": null,
  "beta": 1.610973,
  "circulatingSupply": null,
  "startDate": null,
  "regularMarketDayLow": 0.0025,
  "priceHint": 4,
  "currency": "USD",
  "trailingPE": 0.35714284,
  "regularMarketVolume": 1,
  "lastMarket": null,
  "maxSupply": null,
  "openInterest": null,
  "marketCap": 59972,
  "volumeAllCurrencies": null,
  "strikePrice": null,
  "averageVolume": 2428,
  "priceToSalesTrailing12Months": 0.032853432,
  "dayLow": 0.0025,
  "ask": 0,
  "ytdReturn": null,
  "askSize": 0,
  "volume": 1,
  "fiftyTwoWeekHigh": 0.0045,
  "forwardPE": null,
  "fromCurrency": null,
  "fiveYearAvgDividendYield": null,
  "fiftyTwoWeekLow": 0.0001,
  "bid": 0,
  "tradeable": false,
  "dividendYield": null,
  "bidSize": 0,
  "dayHigh": 0.0025,
  "exchange": "PNK",
  "shortName": "CYBER OPERATIONS INC.",
  "longName": "Cyber Operations, Inc.",
  "exchangeTimezoneName": "America/New_York",
  "exchangeTimezoneShortName": "EST",
  "isEsgPopulated": false,
  "gmtOffSetMilliseconds": "-18000000",
  "underlyingSymbol": null,
  "quoteType": "EQUITY",
  "symbol": "CYPJ",
  "underlyingExchangeSymbol": null,
  "headSymbol": null,
  "messageBoardId": "finmb_7985290",
  "uuid": "7233a877-2abd-38c0-a215-6eba1e2726d8",
  "market": "us_market",
  "annualHoldingsTurnover": null,
  "enterpriseToRevenue": 0.53,
  "beta3Year": null,
  "profitMargins": 0.08974,
  "enterpriseToEbitda": 2.34,
  "52WeekChange": null,
  "morningStarRiskRating": null,
  "forwardEps": null,
  "revenueQuarterlyGrowth": null,
  "sharesOutstanding": 23989000,
  "fundInceptionDate": null,
  "annualReportExpenseRatio": null,
  "bookValue": 0.025,
  "sharesShort": null,
  "sharesPercentSharesOut": null,
  "fundFamily": null,
  "lastFiscalYearEnd": 1293753600,
  "heldPercentInstitutions": null,
  "netIncomeToCommon": 163814,
  "trailingEps": 0.007,
  "lastDividendValue": null,
  "SandP52WeekChange": null,
  "priceToBook": 0.099999994,
  "heldPercentInsiders": null,
  "nextFiscalYearEnd": 1356912000,
  "mostRecentQuarter": 1293753600,
  "shortRatio": null,
  "sharesShortPreviousMonthDate": null,
  "floatShares": null,
  "enterpriseValue": 966849,
  "threeYearAverageReturn": null,
  "lastSplitDate": null,
  "lastSplitFactor": null,
  "legalType": null,
  "morningStarOverallRating": null,
  "earningsQuarterlyGrowth": null,
  "dateShortInterest": null,
  "pegRatio": null,
  "lastCapGain": null,
  "shortPercentOfFloat": null,
  "sharesShortPriorMonth": null,
  "category": null,
  "fiveYearAverageReturn": null,
  "regularMarketPrice": 0.0025,
  "logo_url": "https://logo.clearbit.com/cyberoperations.com"
}