{
  "zip": "21208",
  "sector": "Healthcare",
  "fullTimeEmployees": 2,
  "longBusinessSummary": "The Greater Cannabis Company, Inc., a biopharmaceutical company, focuses on the development and commercialization of technology for transmucosal delivery of legal medical or recreational cannabis and cannabinoids. The company intends to commercialize the technology by sublicensing or partnering with licensed producers, distributors, processors, consumer product, and pharmaceutical companies in the legal cannabis and CBD industries to bring the product to the North American market in legal medical and recreational cannabis and CBD segments. The Greater Cannabis Company, Inc. is based in Baltimore, Maryland.",
  "city": "Baltimore",
  "phone": "443 738 4051",
  "state": "MD",
  "country": "United States",
  "companyOfficers": [],
  "website": "http://www.gcanrx.com",
  "maxAge": 1,
  "address1": "15 Walker Avenue",
  "industry": "Drug Manufacturers—Specialty & Generic",
  "address2": "Suite 101",
  "previousClose": 0.0036,
  "regularMarketOpen": 0.0036,
  "twoHundredDayAverage": 0.004710357,
  "trailingAnnualDividendYield": null,
  "payoutRatio": 0,
  "volume24Hr": null,
  "regularMarketDayHigh": 0.0048,
  "navPrice": null,
  "averageDailyVolume10Day": 23119931,
  "totalAssets": null,
  "regularMarketPreviousClose": 0.0036,
  "fiftyDayAverage": 0.0031524242,
  "trailingAnnualDividendRate": null,
  "open": 0.0036,
  "averageVolume10days": 23119931,
  "expireDate": null,
  "yield": null,
  "algorithm": null,
  "dividendRate": null,
  "exDividendDate": null,
  "beta": 1.607163,
  "circulatingSupply": null,
  "startDate": null,
  "regularMarketDayLow": 0.0035,
  "priceHint": 4,
  "currency": "USD",
  "regularMarketVolume": 36249956,
  "lastMarket": null,
  "maxSupply": null,
  "openInterest": null,
  "marketCap": 1560818,
  "volumeAllCurrencies": null,
  "strikePrice": null,
  "averageVolume": 27078627,
  "priceToSalesTrailing12Months": 29.704971,
  "dayLow": 0.0035,
  "ask": 0,
  "ytdReturn": null,
  "askSize": 0,
  "volume": 36249956,
  "fiftyTwoWeekHigh": 0.0371,
  "forwardPE": null,
  "fromCurrency": null,
  "fiveYearAvgDividendYield": null,
  "fiftyTwoWeekLow": 0.00175,
  "bid": 0,
  "tradeable": false,
  "dividendYield": null,
  "bidSize": 0,
  "dayHigh": 0.0048,
  "exchange": "PNK",
  "shortName": "GREATER CANNABIS CO INC",
  "longName": "The Greater Cannabis Company, Inc.",
  "exchangeTimezoneName": "America/New_York",
  "exchangeTimezoneShortName": "EST",
  "isEsgPopulated": false,
  "gmtOffSetMilliseconds": "-18000000",
  "underlyingSymbol": null,
  "quoteType": "EQUITY",
  "symbol": "GCAN",
  "underlyingExchangeSymbol": null,
  "headSymbol": null,
  "messageBoardId": "finmb_576310974",
  "uuid": "f9feca0d-4823-3908-856f-1f7646d00100",
  "market": "us_market",
  "annualHoldingsTurnover": null,
  "enterpriseToRevenue": 27.979,
  "beta3Year": null,
  "profitMargins": 0,
  "enterpriseToEbitda": -4.111,
  "52WeekChange": null,
  "morningStarRiskRating": null,
  "forwardEps": null,
  "revenueQuarterlyGrowth": null,
  "sharesOutstanding": 332088992,
  "fundInceptionDate": null,
  "annualReportExpenseRatio": null,
  "bookValue": -0.003,
  "sharesShort": null,
  "sharesPercentSharesOut": null,
  "fundFamily": null,
  "lastFiscalYearEnd": 1577750400,
  "heldPercentInstitutions": 0.01327,
  "netIncomeToCommon": -1664417,
  "trailingEps": -0.008,
  "lastDividendValue": null,
  "SandP52WeekChange": null,
  "priceToBook": null,
  "heldPercentInsiders": 0.017,
  "nextFiscalYearEnd": 1640908800,
  "mostRecentQuarter": 1601424000,
  "shortRatio": null,
  "sharesShortPreviousMonthDate": null,
  "floatShares": 327735393,
  "enterpriseValue": 1470120,
  "threeYearAverageReturn": null,
  "lastSplitDate": null,
  "lastSplitFactor": null,
  "legalType": null,
  "morningStarOverallRating": null,
  "earningsQuarterlyGrowth": null,
  "dateShortInterest": null,
  "pegRatio": null,
  "lastCapGain": null,
  "shortPercentOfFloat": null,
  "sharesShortPriorMonth": null,
  "category": null,
  "fiveYearAverageReturn": null,
  "regularMarketPrice": 0.0036,
  "logo_url": "https://logo.clearbit.com/gcanrx.com"
}