{
  "zip": "071000",
  "sector": "Consumer Cyclical",
  "fullTimeEmployees": 59756,
  "longBusinessSummary": "Great Wall Motor Company Limited researches and develops, manufactures, markets, and sells automobiles, and automotive parts and components in China, South Africa, Ecuador, Chile, Russia, Saudi Arabia, and internationally. The company offers pick-up trucks, SUVs, sedans, and energy vehicles primarily under the Haval, WEY, Great Wall Pickup, and ORA brand names; and unmanned vehicles. It also provides auto molds; new energy vehicle transmission and electric drive system; repairs automobiles; and transports general goods, as well as provides truck transportation services. In addition, the company provides investment and financing, logistics, buildings rental, business information and trade consultation, scrap car recycling and dismantling, finance lease, real estate, and after-sales services, as well as automotive technology research, development, and technical consultation services. Further, it processes, recycles, and sells waste and used materials. Additionally, the company engages in the wholesale and retail of car accessories. It also exports its products. The company was formerly known as Baoding Great Wall Motor Company Limited and changed its name to Great Wall Motor Company Limited in May 2003. The company was founded in 1984 and is headquartered in Baoding, China. Great Wall Motor Company Limited is a subsidiary of Baoding Innovation Great Wall Asset Management Company Limited.",
  "city": "Baoding",
  "phone": "86 31 2219 7813",
  "country": "China",
  "companyOfficers": [],
  "website": "http://www.gwm.com.cn",
  "maxAge": 1,
  "address1": "No. 2266 Chaoyang Road South",
  "fax": "86 31 2219 7812",
  "industry": "Auto Manufacturers",
  "previousClose": 3.455,
  "regularMarketOpen": 3.19,
  "twoHundredDayAverage": 1.6148921,
  "trailingAnnualDividendYield": 0.0075253258,
  "payoutRatio": 0.5558,
  "volume24Hr": null,
  "regularMarketDayHigh": 3.34,
  "navPrice": null,
  "averageDailyVolume10Day": 81825,
  "totalAssets": null,
  "regularMarketPreviousClose": 3.455,
  "fiftyDayAverage": 2.7142425,
  "trailingAnnualDividendRate": 0.026,
  "open": 3.19,
  "averageVolume10days": 81825,
  "expireDate": null,
  "yield": null,
  "algorithm": null,
  "dividendRate": 0.04,
  "exDividendDate": 1592784000,
  "beta": 1.491317,
  "circulatingSupply": null,
  "startDate": null,
  "regularMarketDayLow": 3.19,
  "priceHint": 4,
  "currency": "USD",
  "trailingPE": 32.59802,
  "regularMarketVolume": 71982,
  "lastMarket": null,
  "maxSupply": null,
  "openInterest": null,
  "marketCap": 50280214528,
  "volumeAllCurrencies": null,
  "strikePrice": null,
  "averageVolume": 55349,
  "priceToSalesTrailing12Months": null,
  "dayLow": 3.19,
  "ask": 0,
  "ytdReturn": null,
  "askSize": 0,
  "volume": 71982,
  "fiftyTwoWeekHigh": 4.15,
  "forwardPE": null,
  "fromCurrency": null,
  "fiveYearAvgDividendYield": null,
  "fiftyTwoWeekLow": 0.49,
  "bid": 0,
  "tradeable": false,
  "dividendYield": 0.0095,
  "bidSize": 0,
  "dayHigh": 3.34,
  "exchange": "PNK",
  "shortName": "GREAT WALL MOTOR COMPANY LIMITE",
  "longName": "Great Wall Motor Company Limited",
  "exchangeTimezoneName": "America/New_York",
  "exchangeTimezoneShortName": "EST",
  "isEsgPopulated": true,
  "gmtOffSetMilliseconds": "-18000000",
  "underlyingSymbol": null,
  "quoteType": "EQUITY",
  "symbol": "GWLLF",
  "underlyingExchangeSymbol": null,
  "headSymbol": null,
  "messageBoardId": "finmb_8985578",
  "uuid": "d60e797c-f689-3cff-b658-1b4d9e225028",
  "market": "us_market",
  "annualHoldingsTurnover": null,
  "enterpriseToRevenue": null,
  "beta3Year": null,
  "profitMargins": 0.0435,
  "enterpriseToEbitda": null,
  "52WeekChange": null,
  "morningStarRiskRating": null,
  "forwardEps": null,
  "revenueQuarterlyGrowth": null,
  "sharesOutstanding": 3099539968,
  "fundInceptionDate": null,
  "annualReportExpenseRatio": null,
  "bookValue": 0.854,
  "sharesShort": null,
  "sharesPercentSharesOut": null,
  "fundFamily": null,
  "lastFiscalYearEnd": 1577750400,
  "heldPercentInstitutions": 0.27974,
  "netIncomeToCommon": null,
  "trailingEps": 0.101,
  "lastDividendValue": null,
  "SandP52WeekChange": null,
  "priceToBook": 3.8552692,
  "heldPercentInsiders": 0.012259999,
  "nextFiscalYearEnd": 1640908800,
  "mostRecentQuarter": 1601424000,
  "shortRatio": null,
  "sharesShortPreviousMonthDate": null,
  "floatShares": 3993558395,
  "enterpriseValue": 31702919168,
  "threeYearAverageReturn": null,
  "lastSplitDate": 1443571200,
  "lastSplitFactor": "3:1",
  "legalType": null,
  "morningStarOverallRating": null,
  "earningsQuarterlyGrowth": 0.029,
  "dateShortInterest": null,
  "pegRatio": null,
  "lastCapGain": null,
  "shortPercentOfFloat": null,
  "sharesShortPriorMonth": null,
  "category": null,
  "fiveYearAverageReturn": null,
  "regularMarketPrice": 3.19,
  "logo_url": "https://logo.clearbit.com/gwm.com.cn"
}