{
  "zip": "601-8510",
  "sector": "",
  "fullTimeEmployees": 8288,
  "longBusinessSummary": "HORIBA, Ltd. manufactures and sells automotive test, process and environmental, medical-diagnostics, semiconductor, and scientific instruments and systems. Its Automotive Test Systems segment offers emission measurement systems, driveline test systems, automotive emissions analyzers, engine test and brake test systems, and fuel cell and battery test systems; provides vehicle development engineering and testing engineering services; and leases and manages R&D facilities. The company's Process & Environmental Instruments & Systems segment provides stack gas analyzers, industrial water quality analyzers, water quality analysis and examination systems, air pollution analyzers, environmental radiation monitors, and process measurement equipment. Its Medical-Diagnostic Instruments & Systems segment offers hematology and CRP, immunology, clinical chemistry, and blood glucose analyzers. The company's Semiconductor Instruments & Systems segment provides mass flow controllers, chemical concentration monitors, reticle/mask particle detection systems, residual gas analyzers, and vaporizers. Its Scientific Instruments & Systems segment offers Raman spectrometers, pH meters, particle-size distribution analyzers, X-Ray fluorescence analyzers, elemental analyzers, fluorescence spectroscopy/fluorescence lifetime spectroscopy, optical components, spectrometers and detectors, and gratings. HORIBA, Ltd. was founded in 1945 and is headquartered in Kyoto, Japan.",
  "city": "Kyoto",
  "phone": "81 75 313 8121",
  "country": "Japan",
  "companyOfficers": [],
  "website": "http://www.horiba.com",
  "maxAge": 1,
  "address1": "2 Miyanohigashi",
  "industry": "",
  "address2": "Kisshoin Minami-ku",
  "previousClose": 55.5,
  "regularMarketOpen": 55.5,
  "twoHundredDayAverage": 54.2,
  "trailingAnnualDividendYield": null,
  "payoutRatio": null,
  "volume24Hr": null,
  "regularMarketDayHigh": 55.5,
  "navPrice": null,
  "averageDailyVolume10Day": 0,
  "totalAssets": null,
  "regularMarketPreviousClose": 55.5,
  "fiftyDayAverage": 55.11515,
  "trailingAnnualDividendRate": null,
  "open": 55.5,
  "averageVolume10days": 0,
  "expireDate": null,
  "yield": null,
  "algorithm": null,
  "dividendRate": null,
  "exDividendDate": null,
  "beta": 1.185393,
  "circulatingSupply": null,
  "startDate": null,
  "regularMarketDayLow": 55.5,
  "priceHint": 2,
  "currency": "USD",
  "regularMarketVolume": 98,
  "lastMarket": null,
  "maxSupply": null,
  "openInterest": null,
  "marketCap": 1972614272,
  "volumeAllCurrencies": null,
  "strikePrice": null,
  "averageVolume": 11,
  "priceToSalesTrailing12Months": null,
  "dayLow": 55.5,
  "ask": null,
  "ytdReturn": null,
  "askSize": null,
  "volume": 98,
  "fiftyTwoWeekHigh": 62.5,
  "forwardPE": null,
  "fromCurrency": null,
  "fiveYearAvgDividendYield": null,
  "fiftyTwoWeekLow": 48,
  "bid": null,
  "tradeable": false,
  "dividendYield": null,
  "bidSize": null,
  "dayHigh": 55.5,
  "exchange": "PNK",
  "shortName": "HORIBA LTD",
  "longName": "HORIBA, Ltd.",
  "exchangeTimezoneName": "America/New_York",
  "exchangeTimezoneShortName": "EST",
  "isEsgPopulated": false,
  "gmtOffSetMilliseconds": "-18000000",
  "underlyingSymbol": null,
  "quoteType": "EQUITY",
  "symbol": "HRIBF",
  "underlyingExchangeSymbol": null,
  "headSymbol": null,
  "messageBoardId": "finmb_878774",
  "uuid": "2e620014-99be-3a02-aa1d-513acc66609a",
  "market": "us_market",
  "annualHoldingsTurnover": null,
  "enterpriseToRevenue": null,
  "beta3Year": null,
  "profitMargins": 0.07554,
  "enterpriseToEbitda": null,
  "52WeekChange": null,
  "morningStarRiskRating": null,
  "forwardEps": null,
  "revenueQuarterlyGrowth": null,
  "sharesOutstanding": 42170500,
  "fundInceptionDate": null,
  "annualReportExpenseRatio": null,
  "bookValue": null,
  "sharesShort": null,
  "sharesPercentSharesOut": null,
  "fundFamily": null,
  "lastFiscalYearEnd": 1577750400,
  "heldPercentInstitutions": 0.56816,
  "netIncomeToCommon": null,
  "trailingEps": null,
  "lastDividendValue": null,
  "SandP52WeekChange": null,
  "priceToBook": null,
  "heldPercentInsiders": 0.09493,
  "nextFiscalYearEnd": 1640908800,
  "mostRecentQuarter": 1601424000,
  "shortRatio": null,
  "sharesShortPreviousMonthDate": null,
  "floatShares": 38921145,
  "enterpriseValue": 2341952768,
  "threeYearAverageReturn": null,
  "lastSplitDate": null,
  "lastSplitFactor": null,
  "legalType": null,
  "morningStarOverallRating": null,
  "earningsQuarterlyGrowth": 0.003,
  "dateShortInterest": null,
  "pegRatio": null,
  "lastCapGain": null,
  "shortPercentOfFloat": null,
  "sharesShortPriorMonth": null,
  "category": null,
  "fiveYearAverageReturn": null,
  "regularMarketPrice": 55.5,
  "logo_url": "https://logo.clearbit.com/horiba.com"
}