{
  "zip": "R3T 6C6",
  "sector": "Healthcare",
  "longBusinessSummary": "Medicure Inc., a pharmaceutical company, engages in the research, development, and commercialization of therapies for the cardiovascular market in the United States. The company markets and distributes AGGRASTAT injection, a glycoprotein GP IIb/IIIa receptor antagonist for the treatment of acute coronary syndrome, including unstable angina and non-Q-wave myocardial infarction. It also offers ZYPITAMAG to treat patients with primary hyperlipidemia or mixed dyslipidemia; and ReDS, a non-invasive medical device that provides measurement of lung fluid for the management of congestive heart failure, as well as Sodium Nitroprusside injection for the reduction of blood pressure for adult and pediatric patients in hypertensive crisis, as well as for producing controlled hypotension to reduce bleeding during surgery, and for the treatment of acute congestive heart failure. The company was founded in 1997 and is headquartered in Winnipeg, Canada.",
  "city": "Winnipeg",
  "phone": "204 487 7412",
  "state": "MB",
  "country": "Canada",
  "companyOfficers": [],
  "website": "http://www.medicure.com",
  "maxAge": 1,
  "address1": "2-1250 Waverley Street",
  "fax": "204 488 9823",
  "industry": "Biotechnology",
  "previousClose": 1.19,
  "regularMarketOpen": 1.21,
  "twoHundredDayAverage": 0.7584892,
  "trailingAnnualDividendYield": null,
  "payoutRatio": 0,
  "volume24Hr": null,
  "regularMarketDayHigh": 1.23,
  "navPrice": null,
  "averageDailyVolume10Day": 11837,
  "totalAssets": null,
  "regularMarketPreviousClose": 1.19,
  "fiftyDayAverage": 0.82060605,
  "trailingAnnualDividendRate": null,
  "open": 1.21,
  "averageVolume10days": 11837,
  "expireDate": null,
  "yield": null,
  "algorithm": null,
  "dividendRate": null,
  "exDividendDate": null,
  "beta": 0.825742,
  "circulatingSupply": null,
  "startDate": null,
  "regularMarketDayLow": 1.17,
  "priceHint": 4,
  "currency": "USD",
  "regularMarketVolume": 17400,
  "lastMarket": null,
  "maxSupply": null,
  "openInterest": null,
  "marketCap": 12137229,
  "volumeAllCurrencies": null,
  "strikePrice": null,
  "averageVolume": 11379,
  "priceToSalesTrailing12Months": null,
  "dayLow": 1.17,
  "ask": null,
  "ytdReturn": null,
  "askSize": null,
  "volume": 17400,
  "fiftyTwoWeekHigh": 2.87,
  "forwardPE": 1.8,
  "fromCurrency": null,
  "fiveYearAvgDividendYield": null,
  "fiftyTwoWeekLow": 0.56,
  "bid": null,
  "tradeable": false,
  "dividendYield": null,
  "bidSize": null,
  "dayHigh": 1.23,
  "exchange": "PNK",
  "shortName": "MEDICURE INC",
  "longName": "Medicure Inc.",
  "exchangeTimezoneName": "America/New_York",
  "exchangeTimezoneShortName": "EST",
  "isEsgPopulated": false,
  "gmtOffSetMilliseconds": "-18000000",
  "underlyingSymbol": null,
  "quoteType": "EQUITY",
  "symbol": "MCUJF",
  "underlyingExchangeSymbol": null,
  "headSymbol": null,
  "messageBoardId": "finmb_3168463",
  "uuid": "09baf23c-2b0c-3e00-b409-bf7863bdaf86",
  "market": "us_market",
  "annualHoldingsTurnover": null,
  "enterpriseToRevenue": null,
  "beta3Year": null,
  "profitMargins": -1.41375,
  "enterpriseToEbitda": null,
  "52WeekChange": null,
  "morningStarRiskRating": null,
  "forwardEps": 0.65,
  "revenueQuarterlyGrowth": null,
  "sharesOutstanding": 10451300,
  "fundInceptionDate": null,
  "annualReportExpenseRatio": null,
  "bookValue": null,
  "sharesShort": 15076,
  "sharesPercentSharesOut": 0.0017,
  "fundFamily": null,
  "lastFiscalYearEnd": 1577750400,
  "heldPercentInstitutions": 0.33380002,
  "netIncomeToCommon": null,
  "trailingEps": null,
  "lastDividendValue": null,
  "SandP52WeekChange": null,
  "priceToBook": null,
  "heldPercentInsiders": 0.23431998,
  "nextFiscalYearEnd": 1640908800,
  "mostRecentQuarter": 1601424000,
  "shortRatio": 1.77,
  "sharesShortPreviousMonthDate": 1194566400,
  "floatShares": 5535015,
  "enterpriseValue": 12437062,
  "threeYearAverageReturn": null,
  "lastSplitDate": 1351814400,
  "lastSplitFactor": "1:15",
  "legalType": null,
  "morningStarOverallRating": null,
  "earningsQuarterlyGrowth": null,
  "dateShortInterest": 1197331200,
  "pegRatio": -4.64,
  "lastCapGain": null,
  "shortPercentOfFloat": null,
  "sharesShortPriorMonth": 15368,
  "category": null,
  "fiveYearAverageReturn": null,
  "regularMarketPrice": 1.21,
  "logo_url": "https://logo.clearbit.com/medicure.com"
}