{
  "zip": "615-8585",
  "sector": "Technology",
  "fullTimeEmployees": 22161,
  "longBusinessSummary": "ROHM Co., Ltd. manufactures and sells electronic components worldwide. The company offers ICs, including memory, amplifiers and linear, power management, clocks and timers, switches and multiplexers, logic, data converter, sensors and MEMS, digital power, display drivers, motor/actuator driver, interface, communication and speech synthesis LSI, audio and video, and microcontrollers. It also provides discrete semiconductor products, such as diodes, bipolar transistors, and MOSFETs. In addition, the company offers power devices, including SiC power devices, IGBT, IPM, and power diodes and transistors; passive devices, such as resistors, tantalum capacitors, and conductive polymer capacitors; opto devices comprising LEDs, LED displays, laser diodes, and optical sensors; and modules, including power modules, wireless communication modules, print heads, and battery less radio modules, as well as chipsets. Its products are used for the industry, automotive, consumer electronics, and PC/communications applications. The company was formerly known as Toyo Electronics Industry Corporation and changed its name to ROHM Co., Ltd. in 1981. ROHM Co., Ltd. was founded in 1958 and is headquartered in Kyoto, Japan.",
  "city": "Kyoto",
  "phone": "81 75 311 2121",
  "country": "Japan",
  "companyOfficers": [],
  "website": "http://www.rohm.com",
  "maxAge": 1,
  "address1": "21 Saiin Mizosaki-cho",
  "fax": "81 75 315 0172",
  "industry": "Semiconductors",
  "address2": "Ukyo-ku",
  "previousClose": 54.6975,
  "regularMarketOpen": 53.74,
  "twoHundredDayAverage": 38.990864,
  "trailingAnnualDividendYield": 0.023236895,
  "payoutRatio": 0.6399,
  "volume24Hr": null,
  "regularMarketDayHigh": 53.74,
  "navPrice": null,
  "averageDailyVolume10Day": 537,
  "totalAssets": null,
  "regularMarketPreviousClose": 54.6975,
  "fiftyDayAverage": 47.30182,
  "trailingAnnualDividendRate": 1.271,
  "open": 53.74,
  "averageVolume10days": 537,
  "expireDate": null,
  "yield": null,
  "algorithm": null,
  "dividendRate": 0.71,
  "exDividendDate": 1601251200,
  "beta": 1.10623,
  "circulatingSupply": null,
  "startDate": null,
  "regularMarketDayLow": 52.59,
  "priceHint": 2,
  "currency": "USD",
  "trailingPE": 27.171274,
  "regularMarketVolume": 622,
  "lastMarket": null,
  "maxSupply": null,
  "openInterest": null,
  "marketCap": 9442009088,
  "volumeAllCurrencies": null,
  "strikePrice": null,
  "averageVolume": 1023,
  "priceToSalesTrailing12Months": null,
  "dayLow": 52.59,
  "ask": 0,
  "ytdReturn": null,
  "askSize": 0,
  "volume": 622,
  "fiftyTwoWeekHigh": 54.7,
  "forwardPE": null,
  "fromCurrency": null,
  "fiveYearAvgDividendYield": 2.1,
  "fiftyTwoWeekLow": 22.34,
  "bid": 0,
  "tradeable": false,
  "dividendYield": 0.012999999,
  "bidSize": 0,
  "dayHigh": 53.74,
  "exchange": "PNK",
  "shortName": "ROHM CO LTD",
  "longName": "ROHM Co., Ltd.",
  "exchangeTimezoneName": "America/New_York",
  "exchangeTimezoneShortName": "EST",
  "isEsgPopulated": false,
  "gmtOffSetMilliseconds": "-18000000",
  "underlyingSymbol": null,
  "quoteType": "EQUITY",
  "symbol": "ROHCY",
  "underlyingExchangeSymbol": null,
  "headSymbol": null,
  "messageBoardId": "finmb_875769",
  "uuid": "a74fda37-b635-38b6-852a-e43d5f8d029a",
  "market": "us_market",
  "annualHoldingsTurnover": null,
  "enterpriseToRevenue": null,
  "beta3Year": null,
  "profitMargins": 0.07146,
  "enterpriseToEbitda": null,
  "52WeekChange": null,
  "morningStarRiskRating": null,
  "forwardEps": null,
  "revenueQuarterlyGrowth": null,
  "sharesOutstanding": 182260992,
  "fundInceptionDate": null,
  "annualReportExpenseRatio": null,
  "bookValue": 33.491,
  "sharesShort": null,
  "sharesPercentSharesOut": null,
  "fundFamily": null,
  "lastFiscalYearEnd": 1585612800,
  "heldPercentInstitutions": 0.00056,
  "netIncomeToCommon": null,
  "trailingEps": 1.9355,
  "lastDividendValue": null,
  "SandP52WeekChange": null,
  "priceToBook": 1.5702726,
  "heldPercentInsiders": 0,
  "nextFiscalYearEnd": 1648684800,
  "mostRecentQuarter": 1601424000,
  "shortRatio": null,
  "sharesShortPreviousMonthDate": null,
  "floatShares": 191435033,
  "enterpriseValue": 10735541248,
  "threeYearAverageReturn": null,
  "lastSplitDate": null,
  "lastSplitFactor": null,
  "legalType": null,
  "morningStarOverallRating": null,
  "earningsQuarterlyGrowth": -0.331,
  "dateShortInterest": null,
  "pegRatio": null,
  "lastCapGain": null,
  "shortPercentOfFloat": null,
  "sharesShortPriorMonth": null,
  "category": null,
  "fiveYearAverageReturn": null,
  "regularMarketPrice": 53.74,
  "logo_url": "https://logo.clearbit.com/rohm.com"
}