{
  "sector": "Energy",
  "fullTimeEmployees": 4,
  "longBusinessSummary": "Strattner Financial Group Corp., an investment management company, manages multiple alternative asset classes, including private equity, convertibles, credit, and hedge funds. It also focuses on selling satellite based communications devices. The company was formerly known as SC Holdings Corp. and changed its name to Strattner Financial Group Corp. in March 2020. The company was founded in 2012 and is headquartered in Tsim Sha Tsui, Hong Kong.",
  "city": "Tsim Sha Tsui",
  "country": "Hong Kong",
  "companyOfficers": [],
  "website": "http://strattners.com",
  "maxAge": 1,
  "address1": "712, Lippo Sun Plaza",
  "industry": "Oil & Gas E&P",
  "address2": "7Th Floor Canton Road",
  "previousClose": 0.021,
  "regularMarketOpen": 0.024,
  "twoHundredDayAverage": 0.025568346,
  "trailingAnnualDividendYield": null,
  "payoutRatio": 0,
  "volume24Hr": null,
  "regularMarketDayHigh": 0.024,
  "navPrice": null,
  "averageDailyVolume10Day": 180075,
  "totalAssets": null,
  "regularMarketPreviousClose": 0.021,
  "fiftyDayAverage": 0.02030303,
  "trailingAnnualDividendRate": null,
  "open": 0.024,
  "averageVolume10days": 180075,
  "expireDate": null,
  "yield": null,
  "algorithm": null,
  "dividendRate": null,
  "exDividendDate": null,
  "beta": 0.600315,
  "circulatingSupply": null,
  "startDate": null,
  "regularMarketDayLow": 0.02,
  "priceHint": 4,
  "currency": "USD",
  "regularMarketVolume": 64518,
  "lastMarket": null,
  "maxSupply": null,
  "openInterest": null,
  "marketCap": 7414,
  "volumeAllCurrencies": null,
  "strikePrice": null,
  "averageVolume": 82807,
  "priceToSalesTrailing12Months": null,
  "dayLow": 0.02,
  "ask": 0,
  "ytdReturn": null,
  "askSize": 0,
  "volume": 64518,
  "fiftyTwoWeekHigh": 0.06,
  "forwardPE": null,
  "fromCurrency": null,
  "fiveYearAvgDividendYield": null,
  "fiftyTwoWeekLow": 0.002,
  "bid": 0,
  "tradeable": false,
  "dividendYield": null,
  "bidSize": 0,
  "dayHigh": 0.024,
  "exchange": "PNK",
  "shortName": "SC HLDGS CORP",
  "longName": "Strattner Financial Group Corp.",
  "exchangeTimezoneName": "America/New_York",
  "exchangeTimezoneShortName": "EST",
  "isEsgPopulated": false,
  "gmtOffSetMilliseconds": "-18000000",
  "underlyingSymbol": null,
  "quoteType": "EQUITY",
  "symbol": "SCNG",
  "underlyingExchangeSymbol": null,
  "headSymbol": null,
  "messageBoardId": "finmb_20672439",
  "uuid": "6c38c7dc-8f9e-3c10-be31-d94ee9c9698c",
  "market": "us_market",
  "annualHoldingsTurnover": null,
  "enterpriseToRevenue": null,
  "beta3Year": null,
  "profitMargins": 0,
  "enterpriseToEbitda": -13.897,
  "52WeekChange": null,
  "morningStarRiskRating": null,
  "forwardEps": null,
  "revenueQuarterlyGrowth": null,
  "sharesOutstanding": 0,
  "fundInceptionDate": null,
  "annualReportExpenseRatio": null,
  "bookValue": -60.322,
  "sharesShort": null,
  "sharesPercentSharesOut": null,
  "fundFamily": null,
  "lastFiscalYearEnd": 1262217600,
  "heldPercentInstitutions": 0,
  "netIncomeToCommon": -2066000,
  "trailingEps": -23.084,
  "lastDividendValue": null,
  "SandP52WeekChange": null,
  "priceToBook": null,
  "heldPercentInsiders": 0,
  "nextFiscalYearEnd": 1325289600,
  "mostRecentQuarter": 1277856000,
  "shortRatio": null,
  "sharesShortPreviousMonthDate": null,
  "floatShares": null,
  "enterpriseValue": 39535936,
  "threeYearAverageReturn": null,
  "lastSplitDate": 1360540800,
  "lastSplitFactor": "1:20000",
  "legalType": null,
  "morningStarOverallRating": null,
  "earningsQuarterlyGrowth": null,
  "dateShortInterest": null,
  "pegRatio": null,
  "lastCapGain": null,
  "shortPercentOfFloat": null,
  "sharesShortPriorMonth": null,
  "category": null,
  "fiveYearAverageReturn": null,
  "regularMarketPrice": 0.024,
  "logo_url": "https://logo.clearbit.com/strattners.com"
}