{
  "zip": "0160",
  "sector": "Technology",
  "fullTimeEmployees": 23,
  "longBusinessSummary": "Thin Film Electronics ASA designs, develops, and produces ultrathin energy storage solutions for wearable devices, connected sensors, and other applications. Its solid-state lithium battery technology enables it to produce rechargeable batteries with high energy densities and long product lifetimes. The company was founded in 2005 is headquartered in Oslo, Norway.",
  "city": "Oslo",
  "phone": "47 22 42 45 00",
  "country": "Norway",
  "companyOfficers": [],
  "website": "http://www.thinfilmsystems.com",
  "maxAge": 1,
  "address1": "Fridtjof Nansens Plass 4",
  "industry": "Electronic Components",
  "previousClose": 0.45,
  "regularMarketOpen": 0.42,
  "twoHundredDayAverage": 0.20653957,
  "trailingAnnualDividendYield": null,
  "payoutRatio": 0,
  "volume24Hr": null,
  "regularMarketDayHigh": 0.42,
  "navPrice": null,
  "averageDailyVolume10Day": 26412,
  "totalAssets": null,
  "regularMarketPreviousClose": 0.45,
  "fiftyDayAverage": 0.26460606,
  "trailingAnnualDividendRate": null,
  "open": 0.42,
  "averageVolume10days": 26412,
  "expireDate": null,
  "yield": null,
  "algorithm": null,
  "dividendRate": null,
  "exDividendDate": null,
  "beta": 2.124106,
  "circulatingSupply": null,
  "startDate": null,
  "regularMarketDayLow": 0.27,
  "priceHint": 4,
  "currency": "USD",
  "regularMarketVolume": 23200,
  "lastMarket": null,
  "maxSupply": null,
  "openInterest": null,
  "marketCap": 50427004,
  "volumeAllCurrencies": null,
  "strikePrice": null,
  "averageVolume": 5852,
  "priceToSalesTrailing12Months": 101.66734,
  "dayLow": 0.27,
  "ask": 0,
  "ytdReturn": null,
  "askSize": 0,
  "volume": 23200,
  "fiftyTwoWeekHigh": 0.98,
  "forwardPE": -0.88235295,
  "fromCurrency": null,
  "fiveYearAvgDividendYield": null,
  "fiftyTwoWeekLow": 0.1,
  "bid": 0,
  "tradeable": false,
  "dividendYield": null,
  "bidSize": 0,
  "dayHigh": 0.42,
  "exchange": "PNK",
  "shortName": "THIN FILM ELECTRONICS ASA",
  "longName": "Thin Film Electronics ASA",
  "exchangeTimezoneName": "America/New_York",
  "exchangeTimezoneShortName": "EST",
  "isEsgPopulated": false,
  "gmtOffSetMilliseconds": "-18000000",
  "underlyingSymbol": null,
  "quoteType": "EQUITY",
  "symbol": "TFECY",
  "underlyingExchangeSymbol": null,
  "headSymbol": null,
  "messageBoardId": "finmb_740992",
  "uuid": "015ab486-8b10-378f-a294-ce0dcaef1cb3",
  "market": "us_market",
  "annualHoldingsTurnover": null,
  "enterpriseToRevenue": 217.99,
  "beta3Year": null,
  "profitMargins": 0,
  "enterpriseToEbitda": -3.68,
  "52WeekChange": null,
  "morningStarRiskRating": null,
  "forwardEps": -0.34,
  "revenueQuarterlyGrowth": null,
  "sharesOutstanding": 249668992,
  "fundInceptionDate": null,
  "annualReportExpenseRatio": null,
  "bookValue": -0.196,
  "sharesShort": null,
  "sharesPercentSharesOut": null,
  "fundFamily": null,
  "lastFiscalYearEnd": 1577750400,
  "heldPercentInstitutions": null,
  "netIncomeToCommon": -68055000,
  "trailingEps": -1.356,
  "lastDividendValue": null,
  "SandP52WeekChange": null,
  "priceToBook": null,
  "heldPercentInsiders": null,
  "nextFiscalYearEnd": 1640908800,
  "mostRecentQuarter": 1601424000,
  "shortRatio": null,
  "sharesShortPreviousMonthDate": null,
  "floatShares": 128340856,
  "enterpriseValue": 108122960,
  "threeYearAverageReturn": null,
  "lastSplitDate": 1572566400,
  "lastSplitFactor": "1:8",
  "legalType": null,
  "morningStarOverallRating": null,
  "earningsQuarterlyGrowth": null,
  "dateShortInterest": null,
  "pegRatio": null,
  "lastCapGain": null,
  "shortPercentOfFloat": null,
  "sharesShortPriorMonth": null,
  "category": null,
  "fiveYearAverageReturn": null,
  "regularMarketPrice": 0.42,
  "logo_url": "https://logo.clearbit.com/thinfilmsystems.com"
}