{
  "zip": "V6E 3V7",
  "sector": "Basic Materials",
  "longBusinessSummary": "Thunderstruck Resources Ltd. acquires and explores for mineral properties. The company explores for zinc, copper, silver, and gold deposits. Its flagship properties include the Korokayiu and Nakoro projects located on the Island of Viti Levu, Fiji. Thunderstruck Resources Ltd. was incorporated in 2011 and is based in Vancouver, Canada.",
  "city": "Vancouver",
  "phone": "778-840-7180",
  "state": "BC",
  "country": "Canada",
  "companyOfficers": [],
  "website": "http://www.thunderstruck.ca",
  "maxAge": 1,
  "address1": "1090 West Georgia Street",
  "industry": "Other Industrial Metals & Mining",
  "address2": "Suite 488",
  "previousClose": 0.0683,
  "regularMarketOpen": 0.065,
  "twoHundredDayAverage": 0.08477616,
  "trailingAnnualDividendYield": null,
  "payoutRatio": 0,
  "volume24Hr": null,
  "regularMarketDayHigh": 0.065,
  "navPrice": null,
  "averageDailyVolume10Day": 55752,
  "totalAssets": null,
  "regularMarketPreviousClose": 0.0683,
  "fiftyDayAverage": 0.061077274,
  "trailingAnnualDividendRate": null,
  "open": 0.065,
  "averageVolume10days": 55752,
  "expireDate": null,
  "yield": null,
  "algorithm": null,
  "dividendRate": null,
  "exDividendDate": null,
  "beta": 0.20594,
  "circulatingSupply": null,
  "startDate": null,
  "regularMarketDayLow": 0.0545,
  "priceHint": 4,
  "currency": "USD",
  "regularMarketVolume": 193020,
  "lastMarket": null,
  "maxSupply": null,
  "openInterest": null,
  "marketCap": 4228715,
  "volumeAllCurrencies": null,
  "strikePrice": null,
  "averageVolume": 42375,
  "priceToSalesTrailing12Months": null,
  "dayLow": 0.0545,
  "ask": 0,
  "ytdReturn": null,
  "askSize": 0,
  "volume": 193020,
  "fiftyTwoWeekHigh": 0.156,
  "forwardPE": null,
  "fromCurrency": null,
  "fiveYearAvgDividendYield": null,
  "fiftyTwoWeekLow": 0.0301,
  "bid": 0,
  "tradeable": false,
  "dividendYield": null,
  "bidSize": 0,
  "dayHigh": 0.065,
  "exchange": "PNK",
  "shortName": "THUNDERSTRUCK RESOURCES LTD",
  "longName": "Thunderstruck Resources Ltd.",
  "exchangeTimezoneName": "America/New_York",
  "exchangeTimezoneShortName": "EST",
  "isEsgPopulated": false,
  "gmtOffSetMilliseconds": "-18000000",
  "underlyingSymbol": null,
  "quoteType": "EQUITY",
  "symbol": "THURF",
  "underlyingExchangeSymbol": null,
  "headSymbol": null,
  "messageBoardId": "finmb_144476519",
  "uuid": "7aacb69d-bff6-3611-b239-49f35786050e",
  "market": "us_market",
  "annualHoldingsTurnover": null,
  "enterpriseToRevenue": null,
  "beta3Year": null,
  "profitMargins": 0,
  "enterpriseToEbitda": null,
  "52WeekChange": null,
  "morningStarRiskRating": null,
  "forwardEps": null,
  "revenueQuarterlyGrowth": null,
  "sharesOutstanding": 84193504,
  "fundInceptionDate": null,
  "annualReportExpenseRatio": null,
  "bookValue": 0.02,
  "sharesShort": null,
  "sharesPercentSharesOut": null,
  "fundFamily": null,
  "lastFiscalYearEnd": 1577750400,
  "heldPercentInstitutions": 0,
  "netIncomeToCommon": null,
  "trailingEps": -0.009,
  "lastDividendValue": null,
  "SandP52WeekChange": null,
  "priceToBook": 2.725,
  "heldPercentInsiders": 0.09378,
  "nextFiscalYearEnd": 1640908800,
  "mostRecentQuarter": 1601424000,
  "shortRatio": null,
  "sharesShortPreviousMonthDate": null,
  "floatShares": 78123953,
  "enterpriseValue": 5750413,
  "threeYearAverageReturn": null,
  "lastSplitDate": null,
  "lastSplitFactor": null,
  "legalType": null,
  "morningStarOverallRating": null,
  "earningsQuarterlyGrowth": null,
  "dateShortInterest": null,
  "pegRatio": null,
  "lastCapGain": null,
  "shortPercentOfFloat": null,
  "sharesShortPriorMonth": null,
  "category": null,
  "fiveYearAverageReturn": null,
  "regularMarketPrice": 0.065,
  "logo_url": "https://logo.clearbit.com/thunderstruck.ca"
}