{
  "zip": "H2Y 2P5",
  "sector": "Basic Materials",
  "longBusinessSummary": "Vanstar Mining Resources Inc. engages in the acquisition, exploration, development, and operation of mining properties in Canada. It primarily explores for gold deposits. The company's flagship property is the Nelligan project, which consists of 158 cells covering an area of approximately 8,216 hectares located near Chapais in Abitibi. Vanstar Mining Resources Inc. was incorporated in 2007 and is based in Montreal, Canada.",
  "city": "Montreal",
  "phone": "819-763-5096",
  "state": "QC",
  "country": "Canada",
  "companyOfficers": [],
  "website": "http://www.vanstarmining.com",
  "maxAge": 1,
  "address1": "410 rue Saint-Nicolas",
  "industry": "Gold",
  "address2": "Suite 236",
  "previousClose": 1,
  "regularMarketOpen": 0.9981,
  "twoHundredDayAverage": 1.0434535,
  "trailingAnnualDividendYield": null,
  "payoutRatio": 0,
  "volume24Hr": null,
  "regularMarketDayHigh": 1.03,
  "navPrice": null,
  "averageDailyVolume10Day": 98363,
  "totalAssets": null,
  "regularMarketPreviousClose": 1,
  "fiftyDayAverage": 0.9848897,
  "trailingAnnualDividendRate": null,
  "open": 0.9981,
  "averageVolume10days": 98363,
  "expireDate": null,
  "yield": null,
  "algorithm": null,
  "dividendRate": null,
  "exDividendDate": null,
  "beta": 0.963696,
  "circulatingSupply": null,
  "startDate": null,
  "regularMarketDayLow": 0.9611,
  "priceHint": 4,
  "currency": "USD",
  "trailingPE": 39.6,
  "regularMarketVolume": 94383,
  "lastMarket": null,
  "maxSupply": null,
  "openInterest": null,
  "marketCap": 54279920,
  "volumeAllCurrencies": null,
  "strikePrice": null,
  "averageVolume": 104848,
  "priceToSalesTrailing12Months": null,
  "dayLow": 0.9611,
  "ask": 0,
  "ytdReturn": null,
  "askSize": 0,
  "volume": 94383,
  "fiftyTwoWeekHigh": 1.5,
  "forwardPE": null,
  "fromCurrency": null,
  "fiveYearAvgDividendYield": null,
  "fiftyTwoWeekLow": 0.3077,
  "bid": 0,
  "tradeable": false,
  "dividendYield": null,
  "bidSize": 0,
  "dayHigh": 1.03,
  "exchange": "PNK",
  "shortName": "VANSTAR MINING RESOURCES INC",
  "longName": "Vanstar Mining Resources Inc.",
  "exchangeTimezoneName": "America/New_York",
  "exchangeTimezoneShortName": "EST",
  "isEsgPopulated": false,
  "gmtOffSetMilliseconds": "-18000000",
  "underlyingSymbol": null,
  "quoteType": "EQUITY",
  "symbol": "VMNGF",
  "underlyingExchangeSymbol": null,
  "headSymbol": null,
  "messageBoardId": "finmb_51175625",
  "uuid": "773e5368-a1f7-3761-87c0-8c1b45433215",
  "market": "us_market",
  "annualHoldingsTurnover": null,
  "enterpriseToRevenue": null,
  "beta3Year": null,
  "profitMargins": 0,
  "enterpriseToEbitda": null,
  "52WeekChange": null,
  "morningStarRiskRating": null,
  "forwardEps": null,
  "revenueQuarterlyGrowth": null,
  "sharesOutstanding": 55702700,
  "fundInceptionDate": null,
  "annualReportExpenseRatio": null,
  "bookValue": 0.046,
  "sharesShort": null,
  "sharesPercentSharesOut": null,
  "fundFamily": null,
  "lastFiscalYearEnd": 1577750400,
  "heldPercentInstitutions": 0.04239,
  "netIncomeToCommon": null,
  "trailingEps": 0.025,
  "lastDividendValue": null,
  "SandP52WeekChange": null,
  "priceToBook": 21.52174,
  "heldPercentInsiders": 0.06922,
  "nextFiscalYearEnd": 1640908800,
  "mostRecentQuarter": 1601424000,
  "shortRatio": null,
  "sharesShortPreviousMonthDate": null,
  "floatShares": 55589114,
  "enterpriseValue": 55902728,
  "threeYearAverageReturn": null,
  "lastSplitDate": null,
  "lastSplitFactor": null,
  "legalType": null,
  "morningStarOverallRating": null,
  "earningsQuarterlyGrowth": null,
  "dateShortInterest": null,
  "pegRatio": null,
  "lastCapGain": null,
  "shortPercentOfFloat": null,
  "sharesShortPriorMonth": null,
  "category": null,
  "fiveYearAverageReturn": null,
  "regularMarketPrice": 0.9981,
  "logo_url": "https://logo.clearbit.com/vanstarmining.com"
}